launchbox/__init__.py
launchbox/apps.py
launchbox/api/__init__.py
launchbox/api/urls.py
launchbox/api/utils.py
launchbox/api/views/__init__.py
launchbox/api/views/users.py
launchbox/auth/__init__.py
launchbox/identity/__init__.py
launchbox/resources/__init__.py
django_launchbox-1.0.dist-info/LICENSE
django_launchbox-1.0.dist-info/METADATA
django_launchbox-1.0.dist-info/WHEEL
django_launchbox-1.0.dist-info/top_level.txt
django_launchbox-1.0.dist-info/RECORD
