Metadata-Version: 2.1
Name: django-launchbox
Version: 1.0
Summary: A plugin for your Django app to assist in integrating with Launchbox.
Home-page: https://github.com/nasa-jpl/django-launchbox
Author: Jet Propulsion Laboratory
Author-email: Scott Cranfill <scott.cranfill@jpl.nasa.gov>
License: MIT
Project-URL: Homepage, https://github.com/nasa-jpl/django-launchbox
Project-URL: Bug Tracker, https://github.com/nasa-jpl/django-launchbox/issues
Classifier: Environment :: Web Environment
Classifier: Framework :: Django
Classifier: Framework :: Django :: 3.2
Classifier: Framework :: Django :: 4.0
Classifier: Framework :: Django :: 4.1
Classifier: Intended Audience :: Developers
Classifier: License :: OSI Approved :: MIT License
Classifier: Operating System :: OS Independent
Classifier: Programming Language :: Python
Classifier: Programming Language :: Python :: 3
Classifier: Programming Language :: Python :: 3 :: Only
Classifier: Programming Language :: Python :: 3.8
Classifier: Topic :: Internet :: WWW/HTTP
Classifier: Topic :: Internet :: WWW/HTTP :: Dynamic Content
Requires-Python: >=3.8
License-File: LICENSE
Requires-Dist: Django (>=3.2)
Requires-Dist: requests (>=2.28.1)
